swh/__init__.py
swh/loader/__init__.py
swh/loader/npm/__init__.py
swh/loader/npm/client.py
swh/loader/npm/loader.py
swh/loader/npm/tasks.py
swh/loader/npm/utils.py
swh/loader/npm/tests/__init__.py
swh/loader/npm/tests/common.py
swh/loader/npm/tests/test_client.py
swh/loader/npm/tests/test_loader.py
swh/loader/npm/tests/test_utils.py
swh/loader/npm/tests/resources/0b_metadata.json
swh/loader/npm/tests/resources/22u-validators_metadata.json
swh/loader/npm/tests/resources/org_metadata_visit1.json
swh/loader/npm/tests/resources/org_metadata_visit2.json
swh/loader/npm/tests/resources/tarballs/0b-1.0.0.tgz
swh/loader/npm/tests/resources/tarballs/org-0.0.2.tgz
swh/loader/npm/tests/resources/tarballs/org-0.0.3.tgz
swh/loader/npm/tests/resources/tarballs/org-0.0.4.tgz
swh/loader/npm/tests/resources/tarballs/org-0.0.5.tgz
swh/loader/npm/tests/resources/tarballs/org-0.1.0.tgz
swh/loader/npm/tests/resources/tarballs/org-0.2.0.tgz
swh.loader.npm-0.0.7.dist-info/AUTHORS
swh.loader.npm-0.0.7.dist-info/LICENSE
swh.loader.npm-0.0.7.dist-info/METADATA
swh.loader.npm-0.0.7.dist-info/WHEEL
swh.loader.npm-0.0.7.dist-info/top_level.txt
swh.loader.npm-0.0.7.dist-info/RECORD
