Metadata-Version: 2.1
Name: swh.loader.npm
Version: 0.0.7
Summary: Software Heritage loader for npm packages
Home-page: https://forge.softwareheritage.org/source/swh-loader-npm.git
Author: Software Heritage developers
Author-email: swh-devel@inria.fr
License: UNKNOWN
Project-URL: Bug Reports, https://forge.softwareheritage.org/maniphest
Project-URL: Source, https://forge.softwareheritage.org/source/swh-loader-npm
Project-URL: Funding, https://www.softwareheritage.org/donate
Platform: UNKNOWN
Classifier: Programming Language :: Python :: 3
Classifier: Intended Audience :: Developers
Classifier: License :: OSI Approved :: GNU General Public License v3 (GPLv3)
Classifier: Operating System :: OS Independent
Classifier: Development Status :: 3 - Alpha
Requires-Dist: python-dateutil
Requires-Dist: requests
Requires-Dist: setuptools
Requires-Dist: vcversioner
Requires-Dist: chardet
Requires-Dist: swh.model (>=0.0.28)
Requires-Dist: swh.storage (>=0.0.143)
Requires-Dist: swh.scheduler
Requires-Dist: swh.loader.core (>=0.0.40)
Provides-Extra: testing
Requires-Dist: pytest ; extra == 'testing'
Requires-Dist: requests-mock ; extra == 'testing'
Requires-Dist: swh.core[http] (>=0.0.61) ; extra == 'testing'
